setup.py
drawbox/__init__.py
drawbox/draw.py
drawbox.egg-info/PKG-INFO
drawbox.egg-info/SOURCES.txt
drawbox.egg-info/dependency_links.txt
drawbox.egg-info/entry_points.txt
drawbox.egg-info/top_level.txt
drawbox.egg-info/zip-safe