Metadata-Version: 1.0
Name: drawbox
Version: 0.1.1
Summary: a tiny handy cli tool for drawing stack-like box
Home-page: UNKNOWN
Author: c4pt0r
Author-email: i@huangdx.net
License: MIT
Keywords: ascii-art
Platform: UNKNOWN
